{"2024-04-20-2024-04-20": {"VEN - Medios adversos - IG": [{"valor": 52, "palabra": "edmundo-gonz치lez-urrutia"}, {"valor": 22, "palabra": "gonz치lez-urrutia-candidato"}, {"valor": 17, "palabra": "consejo-nacional-electoral"}, {"valor": 16, "palabra": "plataforma-unitaria-democr치tica"}, {"valor": 14, "palabra": "conoce-detalles-nuestra"}, {"valor": 14, "palabra": "detalles-nuestra-tambi칠n"}, {"valor": 14, "palabra": "nuestra-tambi칠n-puedes"}, {"valor": 14, "palabra": "tambi칠n-puedes-llegar"}, {"valor": 14, "palabra": "puedes-llegar-stories"}, {"valor": 14, "palabra": "llegar-stories-destacadas"}, {"valor": 11, "palabra": "art칤culo-completo-nuestra"}, {"valor": 11, "palabra": "completo-nuestra-biograf칤a"}, {"valor": 10, "palabra": "urrutia-candidato-presidencial"}, {"valor": 9, "palabra": "benjam칤n-rausseo-presidente"}, {"valor": 7, "palabra": "completa-nuestra-biograf칤a"}, {"valor": 6, "palabra": "venezuela-pronto-buenas"}, {"valor": 5, "palabra": "embajador-venezuela-argelia"}, {"valor": 5, "palabra": "embajador-edmundo-gonz치lez"}, {"valor": 5, "palabra": "tenemos-candidato-oposici칩n"}, {"valor": 5, "palabra": "candidato-oposici칩n-apoyado"}, {"valor": 5, "palabra": "pr칩rroga-sustituci칩n-modificaci칩n"}, {"valor": 5, "palabra": "sustituci칩n-modificaci칩n-postulaciones"}, {"valor": 5, "palabra": "coalici칩n-nacional-movilizar"}, {"valor": 5, "palabra": "candidatura-edmundo-gonz치lez"}, {"valor": 5, "palabra": "completa-nuestra-p치gina"}, {"valor": 5, "palabra": "nuestra-p치gina-liderendeportescom"}, {"valor": 4, "palabra": "universidad-central-venezuela"}, {"valor": 4, "palabra": "primer-secretario-embajador"}, {"valor": 4, "palabra": "secretario-embajador-venezuela"}, {"valor": 4, "palabra": "nicol치s-maduro-pr칩ximo"}], "VEN - CORINA YORIS - IG": [{"valor": 4, "palabra": "incre칤ble-sucedido-palabras"}, {"valor": 4, "palabra": "sucedido-palabras-pueden"}, {"valor": 4, "palabra": "palabras-pueden-expresar"}, {"valor": 4, "palabra": "pueden-expresar-alegr칤a"}, {"valor": 4, "palabra": "expresar-alegr칤a-muchas"}, {"valor": 4, "palabra": "alegr칤a-muchas-gracias"}, {"valor": 4, "palabra": "muchas-gracias-siempre"}, {"valor": 4, "palabra": "gracias-siempre-estar칠"}, {"valor": 4, "palabra": "siempre-estar칠-contigo"}, {"valor": 4, "palabra": "grandes-retiros-realmente"}, {"valor": 4, "palabra": "retiros-realmente-aprecio"}, {"valor": 3, "palabra": "moroso-salinas-pliego"}, {"valor": 3, "palabra": "taboada-taboada-taboada"}, {"valor": 3, "palabra": "jajajaja-jajajaja-jajajaja"}, {"valor": 2, "palabra": "ricardo-salinas-impuestos"}, {"valor": 2, "palabra": "masivo-xochitl-maynez"}, {"valor": 2, "palabra": "xochitl-maynez-latinus"}, {"valor": 2, "palabra": "maynez-latinus-actual"}, {"valor": 2, "palabra": "latinus-actual-gobierno"}, {"valor": 2, "palabra": "actual-gobierno-empresas"}, {"valor": 2, "palabra": "gobierno-empresas-fantasma"}, {"valor": 2, "palabra": "empresas-fantasma-morena"}, {"valor": 2, "palabra": "fantasma-morena-aliados"}, {"valor": 2, "palabra": "morena-aliados-quitarnos"}, {"valor": 2, "palabra": "pablito-llorar-demostrar"}, {"valor": 2, "palabra": "llorar-demostrar-sigues"}, {"valor": 2, "palabra": "demostrar-sigues-teniendo"}, {"valor": 2, "palabra": "sigues-teniendo-dentro"}, {"valor": 2, "palabra": "impuestos-salinas-pliego"}, {"valor": 2, "palabra": "saquen-afores-azteca"}], "VEN - Medios afines - IG": [{"valor": 13, "palabra": "animador-hispanoam칠rica-fotograf칤a"}, {"valor": 12, "palabra": "edmundo-gonz치lez-urrutia"}, {"valor": 11, "palabra": "ampl칤a-informaciones-nuestra"}, {"valor": 11, "palabra": "informaciones-nuestra-p치gina"}, {"valor": 11, "palabra": "nuestra-p치gina-noticierovenevisionnet"}, {"valor": 7, "palabra": "consejo-nacional-electoral"}, {"valor": 7, "palabra": "hispanoam칠rica-fotograf칤a-vestuario"}, {"valor": 7, "palabra": "nacional-proyectos-pueblo"}, {"valor": 7, "palabra": "millones-litros-gasolina"}, {"valor": 7, "palabra": "litros-gasolina-d칩lares"}, {"valor": 6, "palabra": "presidente-nicol치s-maduro"}, {"valor": 6, "palabra": "consulta-popular-nacional"}, {"valor": 6, "palabra": "popular-nacional-proyectos"}, {"valor": 5, "palabra": "nuestro-presidente-nicol치s"}, {"valor": 5, "palabra": "pareci칩-participaci칩n-recuerda"}, {"valor": 5, "palabra": "participaci칩n-recuerda-dejarle"}, {"valor": 5, "palabra": "recuerda-dejarle-comentario"}, {"valor": 5, "palabra": "dejarle-comentario-participante"}, {"valor": 5, "palabra": "comentario-participante-favorito"}, {"valor": 5, "palabra": "participante-favorito-animador"}, {"valor": 5, "palabra": "favorito-animador-hispanoam칠rica"}, {"valor": 4, "palabra": "gasolina-d칩lares-misera"}, {"valor": 4, "palabra": "tienen-pueblo-controlado"}, {"valor": 4, "palabra": "pueblo-controlado-venezuela"}, {"valor": 4, "palabra": "controlado-venezuela-ustedes"}, {"valor": 4, "palabra": "venezuela-ustedes-maduro"}, {"valor": 4, "palabra": "ustedes-maduro-suficiente"}, {"valor": 4, "palabra": "maduro-suficiente-oportunidad"}, {"valor": 4, "palabra": "detalla-informaci칩n-nuestro"}, {"valor": 4, "palabra": "informaci칩n-nuestro-perfil"}], "VEN - Figuras afines - IG": [{"valor": 31, "palabra": "consulta-popular-nacional"}, {"valor": 29, "palabra": "presidente-nicol치s-maduro"}, {"valor": 20, "palabra": "gobernador-primitivo-cede침o"}, {"valor": 15, "palabra": "nuestro-gobernador-primitivo"}, {"valor": 15, "palabra": "terraza-triada-araure"}, {"valor": 13, "palabra": "nuestro-presidente-nicol치s"}, {"valor": 13, "palabra": "terrazas-tr칤ada-araure"}, {"valor": 10, "palabra": "maduro-nuestro-gobernador"}, {"valor": 10, "palabra": "nicol치s-maduro-nuestro"}, {"valor": 9, "palabra": "primitivo-cede침o-nuestra"}, {"valor": 7, "palabra": "integrar-vencer-patri칩tico"}, {"valor": 7, "palabra": "vencer-patri칩tico-bolivariana"}, {"valor": 7, "palabra": "proclamaci칩n-independencia-venezuela"}, {"valor": 7, "palabra": "nuestra-licenciada-gabriela"}, {"valor": 6, "palabra": "bendiciones-terraza-triada"}, {"valor": 6, "palabra": "terrazas-triada-araure"}, {"valor": 6, "palabra": "viviremos-venceremos-cftp32cojedes"}, {"valor": 6, "palabra": "gracias-nuestro-presidente"}, {"valor": 5, "palabra": "trabajadores-ministerio-tambi칠n"}, {"valor": 5, "palabra": "ministerio-tambi칠n-merecen"}, {"valor": 5, "palabra": "tambi칠n-merecen-misi칩n"}, {"valor": 5, "palabra": "merecen-misi칩n-cuadrantes"}, {"valor": 5, "palabra": "misi칩n-cuadrantes-ministro"}, {"valor": 5, "palabra": "consulta-nacional-popular"}, {"valor": 5, "palabra": "gobernador-ejemplar-primitivo"}, {"valor": 5, "palabra": "bendiciones-nuestro-gobernador"}, {"valor": 5, "palabra": "bendiciones-nuestra-licenciada"}, {"valor": 5, "palabra": "nuestra-embajadora-gabriela"}, {"valor": 5, "palabra": "eliannimar-graterol-terrazas"}, {"valor": 5, "palabra": "graterol-terrazas-triada"}], "VEN - Figuras opositoras - IG": [{"valor": 5, "palabra": "edmundo-gonz치lez-urrutia"}, {"valor": 2, "palabra": "embajador-edmundo-gonz치lez"}, {"valor": 2, "palabra": "venezuela-edmundo-gonz치lez"}, {"valor": 2, "palabra": "gonz치lez-urrutia-nuestro"}, {"valor": 2, "palabra": "edmundo-gonz치lez-candidato"}, {"valor": 2, "palabra": "nuestra-corina-machado"}, {"valor": 2, "palabra": "candidato-unidad-edmundo"}, {"valor": 2, "palabra": "celebrando-legado-conmemoramos"}, {"valor": 2, "palabra": "legado-conmemoramos-centenario"}, {"valor": 2, "palabra": "conmemoramos-centenario-nuestro"}, {"valor": 2, "palabra": "centenario-nuestro-compa침ero"}, {"valor": 2, "palabra": "nuestro-compa침ero-pi침erua"}, {"valor": 2, "palabra": "compa침ero-pi침erua-huella"}, {"valor": 2, "palabra": "pi침erua-huella-imborrable"}, {"valor": 2, "palabra": "huella-imborrable-historia"}, {"valor": 2, "palabra": "imborrable-historia-venezuela"}, {"valor": 2, "palabra": "historia-venezuela-cercan칤a"}, {"valor": 2, "palabra": "venezuela-cercan칤a-incansable"}, {"valor": 2, "palabra": "cercan칤a-incansable-justicia"}, {"valor": 2, "palabra": "incansable-justicia-social"}, {"valor": 2, "palabra": "justicia-social-reflejan"}, {"valor": 2, "palabra": "social-reflejan-esp칤ritu"}, {"valor": 2, "palabra": "reflejan-esp칤ritu-verdadero"}, {"valor": 2, "palabra": "esp칤ritu-verdadero-resguarde"}, {"valor": 2, "palabra": "verdadero-resguarde-respete"}, {"valor": 2, "palabra": "resguarde-respete-condenado"}, {"valor": 2, "palabra": "respete-condenado-fracaso"}, {"valor": 2, "palabra": "condenado-fracaso-inevitable"}, {"valor": 2, "palabra": "fracaso-inevitable-pi침erua"}, {"valor": 2, "palabra": "venezuela-resetea-reinventa"}], "VEN - CORINA MACHADO - IG": [{"valor": 17, "palabra": "edmundo-gonz치lez-urrutia"}, {"valor": 11, "palabra": "libertad-estamos-unidos"}, {"valor": 11, "palabra": "estamos-unidos-fuertes"}, {"valor": 6, "palabra": "edmundo-gonz치lez-candidato"}, {"valor": 6, "palabra": "plataforma-unitaria-democr치tica"}, {"valor": 5, "palabra": "embajador-edmundo-gonz치lez"}, {"valor": 5, "palabra": "unidad-unidad-unidad"}, {"valor": 4, "palabra": "valiente-corina-machado"}, {"valor": 4, "palabra": "nuestros-compa침eros-dignora"}, {"valor": 4, "palabra": "compa침eros-dignora-hern치ndez"}, {"valor": 4, "palabra": "dignora-hern치ndez-alviarez"}, {"valor": 3, "palabra": "representadas-plataforma-unitaria"}, {"valor": 3, "palabra": "conforman-plataforma-unitaria"}, {"valor": 3, "palabra": "venezuela-corina-machado"}, {"valor": 3, "palabra": "edmundo-gonz치lez-presidente"}, {"valor": 3, "palabra": "edmundo-presidente-corina"}, {"valor": 3, "palabra": "nuestra-valiente-corina"}, {"valor": 3, "palabra": "cumple-secuestro-nuestros"}, {"valor": 3, "palabra": "secuestro-nuestros-compa침eros"}, {"valor": 3, "palabra": "hern치ndez-alviarez-v칤ctimas"}, {"valor": 3, "palabra": "alviarez-v칤ctimas-desaparici칩n"}, {"valor": 3, "palabra": "v칤ctimas-desaparici칩n-forzada"}, {"valor": 3, "palabra": "desaparici칩n-forzada-tambi칠n"}, {"valor": 3, "palabra": "forzada-tambi칠n-cumple"}, {"valor": 3, "palabra": "tambi칠n-cumple-persecuci칩n"}, {"valor": 3, "palabra": "cumple-persecuci칩n-r칠gimen"}, {"valor": 3, "palabra": "nuestros-compa침eros-magalli"}, {"valor": 3, "palabra": "compa침eros-magalli-humberto"}, {"valor": 3, "palabra": "magalli-humberto-villalobos"}, {"valor": 3, "palabra": "humberto-villalobos-claudia"}], "VEN - Nicol치s Maduro - IG": [{"valor": 5, "palabra": "presidente-nicol치s-maduro"}, {"valor": 4, "palabra": "jajajaja-jajajaja-jajajaja"}, {"valor": 3, "palabra": "buenas-tardes-presidente"}, {"valor": 3, "palabra": "buenas-tardes-camarada"}, {"valor": 2, "palabra": "operaci칩n-cataratas-porfavor"}, {"valor": 2, "palabra": "buenas-noches-presidente"}, {"valor": 2, "palabra": "materiales-construcci칩n-terminar"}, {"valor": 2, "palabra": "presidente-hablar-ingl칠s"}, {"valor": 2, "palabra": "presidente-maduro-cuenta"}, {"valor": 2, "palabra": "sueldo-empleados-p칰blicos"}, {"valor": 2, "palabra": "empleados-p칰blicos-justicia"}, {"valor": 2, "palabra": "p칰blicos-justicia-social"}, {"valor": 2, "palabra": "justicia-social-venezolanos"}, {"valor": 2, "palabra": "social-venezolanos-pensiones"}, {"valor": 2, "palabra": "venezolanos-pensiones-dignas"}, {"valor": 2, "palabra": "pensiones-dignas-familia"}, {"valor": 2, "palabra": "dignas-familia-militar"}, {"valor": 2, "palabra": "familia-militar-venceremos"}, {"valor": 2, "palabra": "opini칩n-p칰blica-internacional"}, {"valor": 2, "palabra": "maduro-reciba-cordial"}, {"valor": 2, "palabra": "defender-chabestia-publicidad"}, {"valor": 2, "palabra": "millones-litros-gasolina"}, {"valor": 2, "palabra": "litros-gasolina-d칩lares"}, {"valor": 2, "palabra": "gasolina-d칩lares-misera"}, {"valor": 2, "palabra": "d칩lares-misera-tienen"}, {"valor": 2, "palabra": "misera-tienen-pueblo"}, {"valor": 2, "palabra": "tienen-pueblo-controlado"}, {"valor": 2, "palabra": "pueblo-controlado-venezuela"}, {"valor": 2, "palabra": "controlado-venezuela-ustedes"}, {"valor": 2, "palabra": "venezuela-ustedes-maduro"}]}, "2024-04-21-2024-04-21": {"VEN - Medios adversos - IG": [{"valor": 35, "palabra": "edmundo-gonz치lez-urrutia"}, {"valor": 12, "palabra": "conoce-detalles-nuestra"}, {"valor": 12, "palabra": "detalles-nuestra-tambi칠n"}, {"valor": 12, "palabra": "nuestra-tambi칠n-puedes"}, {"valor": 12, "palabra": "tambi칠n-puedes-llegar"}, {"valor": 12, "palabra": "puedes-llegar-stories"}, {"valor": 12, "palabra": "llegar-stories-destacadas"}, {"valor": 10, "palabra": "piram칤des-lotodatos-imanloto"}, {"valor": 10, "palabra": "lotodatos-imanloto-jaladora"}, {"valor": 10, "palabra": "imanloto-jaladora-ayudar"}, {"valor": 10, "palabra": "jaladora-ayudar-comprador"}, {"valor": 10, "palabra": "ayudar-comprador-ponerlo"}, {"valor": 10, "palabra": "comprador-ponerlo-carrera"}, {"valor": 10, "palabra": "ponerlo-carrera-loter칤a"}, {"valor": 10, "palabra": "carrera-loter칤a-obligatorio"}, {"valor": 10, "palabra": "loter칤a-obligatorio-comprar"}, {"valor": 10, "palabra": "obligatorio-comprar-n칰meros"}, {"valor": 10, "palabra": "comprar-n칰meros-cliente"}, {"valor": 10, "palabra": "n칰meros-cliente-compra"}, {"valor": 10, "palabra": "cliente-compra-atracci칩n"}, {"valor": 10, "palabra": "compra-atracci칩n-energ칤a"}, {"valor": 10, "palabra": "atracci칩n-energ칤a-positiva"}, {"valor": 10, "palabra": "energ칤a-positiva-positivoen"}, {"valor": 10, "palabra": "positiva-positivoen-momento"}, {"valor": 10, "palabra": "positivoen-momento-aquien"}, {"valor": 9, "palabra": "completa-nuestra-biograf칤a"}, {"valor": 9, "palabra": "consejo-nacional-electoral"}, {"valor": 9, "palabra": "art칤culo-completo-nuestra"}, {"valor": 9, "palabra": "completo-nuestra-biograf칤a"}, {"valor": 8, "palabra": "plataforma-unitaria-democr치tica"}], "VEN - CORINA YORIS - IG": [{"valor": 5, "palabra": "adri치n-v치zquez-m칠xico"}, {"valor": 4, "palabra": "votemos-contra-morena"}, {"valor": 4, "palabra": "trabajar-iniciativa-privada"}, {"valor": 3, "palabra": "contra-morena-quit칠mosle"}, {"valor": 3, "palabra": "segundo-debate-jefatura"}, {"valor": 3, "palabra": "segundo-debate-chilango"}, {"valor": 3, "palabra": "investiga-칰ltima-intentaron"}, {"valor": 3, "palabra": "칰ltima-intentaron-versi칩n"}, {"valor": 3, "palabra": "intentaron-versi칩n-analizaron"}, {"valor": 3, "palabra": "versi칩n-analizaron-oscuro"}, {"valor": 3, "palabra": "analizaron-oscuro-cambiaron"}, {"valor": 3, "palabra": "oscuro-cambiaron-fueran"}, {"valor": 3, "palabra": "cambiaron-fueran-cuentas"}, {"valor": 3, "palabra": "fueran-cuentas-inactivas"}, {"valor": 3, "palabra": "cuentas-inactivas-humano"}, {"valor": 3, "palabra": "inactivas-humano-verdad"}, {"valor": 3, "palabra": "humano-verdad-quisieran"}, {"valor": 3, "palabra": "verdad-quisieran-beneficiar"}, {"valor": 3, "palabra": "quisieran-beneficiar-dinero"}, {"valor": 3, "palabra": "beneficiar-dinero-dar칤as"}, {"valor": 3, "palabra": "dinero-dar칤as-buscar"}, {"valor": 3, "palabra": "dar칤as-buscar-pasado"}, {"valor": 3, "palabra": "buscar-pasado-trabajadores"}, {"valor": 3, "palabra": "pasado-trabajadores-leg칤timos"}, {"valor": 3, "palabra": "trabajadores-leg칤timos-beneficiados"}, {"valor": 3, "palabra": "leg칤timos-beneficiados-motivo"}, {"valor": 3, "palabra": "beneficiados-motivo-tocado"}, {"valor": 3, "palabra": "motivo-tocado-dinero"}, {"valor": 3, "palabra": "tocado-dinero-manera"}, {"valor": 3, "palabra": "dinero-manera-honesta"}], "VEN - Medios afines - IG": [{"valor": 29, "palabra": "consulta-popular-nacional"}, {"valor": 19, "palabra": "detalla-informaci칩n-nuestro"}, {"valor": 19, "palabra": "informaci칩n-nuestro-perfil"}, {"valor": 12, "palabra": "presidente-nicol치s-maduro"}, {"valor": 6, "palabra": "edmundo-gonz치lez-urrutia"}, {"valor": 5, "palabra": "animador-hispanoam칠rica-fotograf칤a"}, {"valor": 5, "palabra": "洧딌洧딮洧딭洧洧땍洧딫洧때洧딡-洧딖洧딮洧딯洧땍洧딫洧딡洧-洧디洧딡洧딣洧딨洧딮洧딭洧딡洧딫"}, {"valor": 5, "palabra": "rep칰blica-bolivariana-venezuela"}, {"valor": 5, "palabra": "venezuela-nicol치s-maduro"}, {"valor": 4, "palabra": "presidente-rep칰blica-bolivariana"}, {"valor": 4, "palabra": "bolivariana-venezuela-nicol치s"}, {"valor": 4, "palabra": "comunas-consejos-comunales"}, {"valor": 4, "palabra": "popular-nacional-proyectos"}, {"valor": 4, "palabra": "coordinador-estadal-partido"}, {"valor": 4, "palabra": "estadal-partido-bol칤var"}, {"valor": 4, "palabra": "maduro-pueblo-quiere"}, {"valor": 4, "palabra": "jajajaja-jajajaja-jajajaja"}, {"valor": 4, "palabra": "votaron-millones-personas"}, {"valor": 3, "palabra": "captado-atenci칩n-internacional"}, {"valor": 3, "palabra": "atenci칩n-internacional-presencia"}, {"valor": 3, "palabra": "veedores-encuentra-soci칩logo"}, {"valor": 3, "palabra": "encuentra-soci칩logo-puerto"}, {"valor": 3, "palabra": "soci칩logo-puerto-grosfoguel"}, {"valor": 3, "palabra": "puerto-grosfoguel-destac칩"}, {"valor": 3, "palabra": "grosfoguel-destac칩-jornada"}, {"valor": 3, "palabra": "destac칩-jornada-reflejo"}, {"valor": 3, "palabra": "consejo-nacional-electoral"}, {"valor": 3, "palabra": "consejos-comunales-comunas"}, {"valor": 3, "palabra": "ejecutar치-financiar치-espacio"}, {"valor": 3, "palabra": "financiar치-espacio-comunidades"}], "VEN - Figuras afines - IG": [{"valor": 84, "palabra": "consulta-popular-nacional"}, {"valor": 12, "palabra": "presidenta-consejo-legislativo"}, {"valor": 12, "palabra": "consejo-legislativo-estado"}, {"valor": 12, "palabra": "legislativo-estado-barinas"}, {"valor": 11, "palabra": "presidente-nicol치s-maduro"}, {"valor": 8, "palabra": "coordinador-estadal-partido"}, {"valor": 8, "palabra": "estadal-partido-bol칤var"}, {"valor": 7, "palabra": "popular-nacional-venezuela"}, {"valor": 7, "palabra": "participar-consulta-popular"}, {"valor": 7, "palabra": "venezuela-activo-galindo"}, {"valor": 6, "palabra": "democracia-participativa-protag칩nica"}, {"valor": 6, "palabra": "participando-consulta-popular"}, {"valor": 6, "palabra": "importante-consulta-popular"}, {"valor": 6, "palabra": "nacional-venezuela-destaca"}, {"valor": 6, "palabra": "venezuela-destaca-popular"}, {"valor": 6, "palabra": "destaca-popular-transformaci칩n"}, {"valor": 6, "palabra": "popular-transformaci칩n-barinas"}, {"valor": 6, "palabra": "transformaci칩n-barinas-dessiree"}, {"valor": 6, "palabra": "barinas-dessiree-contreras"}, {"valor": 6, "palabra": "dessiree-contreras-presidenta"}, {"valor": 6, "palabra": "contreras-presidenta-consejo"}, {"valor": 6, "palabra": "estado-barinas-enfatiz칩"}, {"valor": 6, "palabra": "barinas-enfatiz칩-trascendencia"}, {"valor": 6, "palabra": "enfatiz칩-trascendencia-consulta"}, {"valor": 6, "palabra": "trascendencia-consulta-popular"}, {"valor": 6, "palabra": "popular-nacional-llevando"}, {"valor": 6, "palabra": "nacional-llevando-destacando"}, {"valor": 6, "palabra": "llevando-destacando-importancia"}, {"valor": 6, "palabra": "destacando-importancia-esp칤ritu"}, {"valor": 6, "palabra": "importancia-esp칤ritu-comunitario"}], "VEN - Figuras opositoras - IG": [{"valor": 8, "palabra": "edmundo-gonz치lez-urrutia"}, {"valor": 4, "palabra": "tenemos-candidato-edmundo"}, {"valor": 4, "palabra": "candidato-edmundo-gonz치lez"}, {"valor": 3, "palabra": "venezuela-tenemos-candidato"}, {"valor": 3, "palabra": "gonz치lez-urrutia-candidato"}, {"valor": 3, "palabra": "urrutia-candidato-unidad"}, {"valor": 3, "palabra": "candidato-unidad-partidos"}, {"valor": 3, "palabra": "unidad-partidos-verdadera"}, {"valor": 3, "palabra": "partidos-verdadera-oposici칩n"}, {"valor": 3, "palabra": "verdadera-oposici칩n-sector"}, {"valor": 3, "palabra": "oposici칩n-sector-mujeres"}, {"valor": 3, "palabra": "sector-mujeres-queremos"}, {"valor": 3, "palabra": "mujeres-queremos-destacar"}, {"valor": 3, "palabra": "queremos-destacar-participaci칩n"}, {"valor": 3, "palabra": "destacar-participaci칩n-mujeres"}, {"valor": 3, "palabra": "participaci칩n-mujeres-pol칤ticas"}, {"valor": 3, "palabra": "mujeres-pol칤ticas-quienes"}, {"valor": 3, "palabra": "pol칤ticas-quienes-trascendentales"}, {"valor": 3, "palabra": "quienes-trascendentales-lograr"}, {"valor": 3, "palabra": "trascendentales-lograr-transici칩n"}, {"valor": 3, "palabra": "lograr-transici칩n-democr치tica"}, {"valor": 3, "palabra": "transici칩n-democr치tica-comprometidas"}, {"valor": 3, "palabra": "democr치tica-comprometidas-fuerza"}, {"valor": 3, "palabra": "comprometidas-fuerza-seguir"}, {"valor": 3, "palabra": "fuerza-seguir-articulando"}, {"valor": 3, "palabra": "seguir-articulando-organizando"}, {"valor": 3, "palabra": "articulando-organizando-movilizando"}, {"valor": 3, "palabra": "organizando-movilizando-cambio"}, {"valor": 3, "palabra": "movilizando-cambio-merecemos"}, {"valor": 3, "palabra": "cambio-merecemos-comprometidas"}], "VEN - CORINA MACHADO - IG": [{"valor": 15, "palabra": "edmundo-gonz치lez-urrutia"}, {"valor": 5, "palabra": "habilita-habilita-habilita"}, {"valor": 4, "palabra": "estamos-unidos-fuertes"}, {"valor": 4, "palabra": "candidato-edmundo-gonz치lez"}, {"valor": 4, "palabra": "quiero-enviarles-mensaje"}, {"valor": 4, "palabra": "enviarles-mensaje-ustedes"}, {"valor": 4, "palabra": "mensaje-ustedes-seguido"}, {"valor": 4, "palabra": "ustedes-seguido-atenci칩n"}, {"valor": 4, "palabra": "seguido-atenci칩n-cruciales"}, {"valor": 4, "palabra": "atenci칩n-cruciales-vivimos"}, {"valor": 4, "palabra": "cruciales-vivimos-porque"}, {"valor": 4, "palabra": "vivimos-porque-sabemos"}, {"valor": 4, "palabra": "porque-sabemos-hagamos"}, {"valor": 4, "palabra": "sabemos-hagamos-venezolanos"}, {"valor": 4, "palabra": "hagamos-venezolanos-marcar치"}, {"valor": 4, "palabra": "venezolanos-marcar치-millones"}, {"valor": 4, "palabra": "marcar치-millones-venezolanos"}, {"valor": 4, "palabra": "millones-venezolanos-pr칩ximas"}, {"valor": 4, "palabra": "venezolanos-pr칩ximas-d칠cadas"}, {"valor": 4, "palabra": "pr칩ximas-d칠cadas-muchas"}, {"valor": 4, "palabra": "d칠cadas-muchas-personas"}, {"valor": 4, "palabra": "muchas-personas-incluso"}, {"valor": 4, "palabra": "personas-incluso-an칩nimas"}, {"valor": 4, "palabra": "incluso-an칩nimas-arriesgado"}, {"valor": 4, "palabra": "an칩nimas-arriesgado-naci칩n"}, {"valor": 4, "palabra": "arriesgado-naci칩n-luminosa"}, {"valor": 4, "palabra": "naci칩n-luminosa-gracias"}, {"valor": 4, "palabra": "luminosa-gracias-permitido"}, {"valor": 4, "palabra": "gracias-permitido-cruzara"}, {"valor": 4, "palabra": "permitido-cruzara-venezolanos"}], "VEN - Nicol치s Maduro - IG": [{"valor": 8, "palabra": "venezuela-activo-galindo"}, {"valor": 5, "palabra": "victoria-venezuela-activo"}, {"valor": 5, "palabra": "activo-galindo-venezuela"}, {"valor": 5, "palabra": "jordan-pasar치-pueblo"}, {"valor": 5, "palabra": "pasar치-pueblo-abrir칠"}, {"valor": 5, "palabra": "pueblo-abrir칠-caminos"}, {"valor": 4, "palabra": "presidente-nicol치s-maduro"}, {"valor": 4, "palabra": "juntos-ministro-rafael"}, {"valor": 4, "palabra": "ministro-rafael-tellechea"}, {"valor": 4, "palabra": "galindo-venezuela-activo"}, {"valor": 3, "palabra": "nuestro-compromiso-victoria"}, {"valor": 3, "palabra": "nicol치s-maduro-victoria"}, {"valor": 3, "palabra": "maduro-victoria-venezuela"}, {"valor": 3, "palabra": "trabajando-venezuela-activo"}, {"valor": 2, "palabra": "consulta-popular-nacional"}, {"valor": 2, "palabra": "presidente-necesito-hablar"}, {"valor": 2, "palabra": "buenos-estimado-presidente"}, {"valor": 2, "palabra": "estimado-presidente-nicolas"}, {"valor": 2, "palabra": "presidente-nicolas-maduro"}, {"valor": 2, "palabra": "nicolas-maduro-solicito"}, {"valor": 2, "palabra": "maduro-solicito-intermediaci칩n"}, {"valor": 2, "palabra": "solicito-intermediaci칩n-esperando"}, {"valor": 2, "palabra": "intermediaci칩n-esperando-cancele"}, {"valor": 2, "palabra": "esperando-cancele-prestaciones"}, {"valor": 2, "palabra": "cancele-prestaciones-sociales"}, {"valor": 2, "palabra": "prestaciones-sociales-ahorros"}, {"valor": 2, "palabra": "sociales-ahorros-ipasme"}, {"valor": 2, "palabra": "ahorros-ipasme-educador"}, {"valor": 2, "palabra": "ipasme-educador-jubilado"}, {"valor": 2, "palabra": "educador-jubilado-aragua"}]}}