{"2024-06-24-2024-06-24": {"VEN - Figuras opositoras - IG": [{"valor": 11, "palabra": "edmundo-gonzález"}, {"valor": 7, "palabra": "gracias-gracias"}, {"valor": 4, "palabra": "libertad-libertad"}, {"valor": 4, "palabra": "libertad-venezuela"}, {"valor": 4, "palabra": "batalla-carabobo"}, {"valor": 3, "palabra": "gonzález-urrutia"}, {"valor": 3, "palabra": "muchas-bendiciones"}, {"valor": 3, "palabra": "libertad-gracias"}, {"valor": 3, "palabra": "cumpleaños-bendiciones"}, {"valor": 3, "palabra": "orgullo-venezolano"}, {"valor": 3, "palabra": "bendiciones-venezuela"}, {"valor": 2, "palabra": "venezuela-herida"}, {"valor": 2, "palabra": "éxitos-bendiciones"}, {"valor": 2, "palabra": "felicidades-bendiciones"}, {"valor": 2, "palabra": "bruselas-logran"}, {"valor": 2, "palabra": "felicitaciones-bendiciones"}, {"valor": 2, "palabra": "venezuela-merece"}, {"valor": 2, "palabra": "muchas-gracias"}, {"valor": 2, "palabra": "bendiga-edmundo"}, {"valor": 2, "palabra": "corina-machado"}, {"valor": 2, "palabra": "quienes-dejaron"}, {"valor": 2, "palabra": "repiquen-tambores"}, {"valor": 2, "palabra": "acción-democrática"}, {"valor": 2, "palabra": "tarjeta-manito"}, {"valor": 2, "palabra": "gonzález-presidente"}, {"valor": 2, "palabra": "seguimos-trabajando"}, {"valor": 2, "palabra": "trabajando-lograr"}, {"valor": 2, "palabra": "lograr-cambio"}, {"valor": 2, "palabra": "recordamos-podemos"}, {"valor": 2, "palabra": "podemos-depositar"}], "VEN - Medios afines - IG": [{"valor": 26, "palabra": "edmundo-gonzález"}, {"valor": 26, "palabra": "batalla-carabobo"}, {"valor": 23, "palabra": "edmundo-presidente"}, {"valor": 22, "palabra": "nicolás-maduro"}, {"valor": 16, "palabra": "presidente-maduro"}, {"valor": 15, "palabra": "gonzález-presidente"}, {"valor": 15, "palabra": "presidente-venezuela"}, {"valor": 12, "palabra": "cristóbal-mendoza"}, {"valor": 12, "palabra": "república-bolivariana"}, {"valor": 12, "palabra": "pueblo-venezolano"}, {"valor": 11, "palabra": "fuerzas-armadas"}, {"valor": 11, "palabra": "presidente-república"}, {"valor": 10, "palabra": "bolivariana-venezuela"}, {"valor": 9, "palabra": "edmundo-corina"}, {"valor": 9, "palabra": "jajaja-jajaja"}, {"valor": 9, "palabra": "jajajaja-jajajaja"}, {"valor": 8, "palabra": "corina-machado"}, {"valor": 8, "palabra": "ejército-bolivariano"}, {"valor": 8, "palabra": "fuerza-armada"}, {"valor": 8, "palabra": "ministro-anibal"}, {"valor": 7, "palabra": "venezuela-nicolás"}, {"valor": 7, "palabra": "estado-carabobo"}, {"valor": 7, "palabra": "sistema-eléctrico"}, {"valor": 7, "palabra": "guardia-nacional"}, {"valor": 7, "palabra": "carabobo-ejército"}, {"valor": 7, "palabra": "síguenos-nuestras"}, {"valor": 7, "palabra": "inmaterial-humanidad"}, {"valor": 7, "palabra": "nuestras-sociales"}, {"valor": 7, "palabra": "servicios-públicos"}, {"valor": 7, "palabra": "festival-poesía"}], "VEN - Medios adversos - IG": [{"valor": 57, "palabra": "edmundo-presidente"}, {"valor": 44, "palabra": "estados-unidos"}, {"valor": 31, "palabra": "edmundo-gonzález"}, {"valor": 26, "palabra": "nicolás-maduro"}, {"valor": 25, "palabra": "corina-machado"}, {"valor": 17, "palabra": "artículo-completo"}, {"valor": 14, "palabra": "batalla-carabobo"}, {"valor": 13, "palabra": "fuerzas-armadas"}, {"valor": 13, "palabra": "pueblo-venezolano"}, {"valor": 13, "palabra": "presidente-venezuela"}, {"valor": 13, "palabra": "también-puedes"}, {"valor": 12, "palabra": "centro-electoral"}, {"valor": 12, "palabra": "maduro-presidente"}, {"valor": 11, "palabra": "presidente-pueblo"}, {"valor": 11, "palabra": "conoce-también"}, {"valor": 11, "palabra": "privatizar-servicios"}, {"valor": 11, "palabra": "servicios-públicos"}, {"valor": 11, "palabra": "pueblo-venezuela"}, {"valor": 10, "palabra": "gonzález-urrutia"}, {"valor": 10, "palabra": "cadena-perpetua"}, {"valor": 10, "palabra": "amplía-noticias"}, {"valor": 10, "palabra": "fuerza-armada"}, {"valor": 10, "palabra": "inabilitada-privatizar"}, {"valor": 10, "palabra": "públicos-educación"}, {"valor": 10, "palabra": "educación-pensiones"}, {"valor": 10, "palabra": "pensiones-eliminar"}, {"valor": 10, "palabra": "eliminar-guardia"}, {"valor": 10, "palabra": "guardia-nacional"}, {"valor": 10, "palabra": "nacional-inmundo"}, {"valor": 10, "palabra": "inmundo-presidente"}], "VEN - Figuras afines - IG": [{"valor": 99, "palabra": "batalla-carabobo"}, {"valor": 57, "palabra": "nicolás-maduro"}, {"valor": 47, "palabra": "ejército-bolivariano"}, {"valor": 33, "palabra": "primitivo-cedeño"}, {"valor": 30, "palabra": "presidente-nicolás"}, {"valor": 25, "palabra": "carabobo-ejército"}, {"valor": 25, "palabra": "independencia-venezuela"}, {"valor": 20, "palabra": "ejército-realista"}, {"valor": 17, "palabra": "libertador-bolívar"}, {"valor": 15, "palabra": "fuerza-armada"}, {"valor": 15, "palabra": "hombres-mujeres"}, {"valor": 14, "palabra": "revolución-bolivariana"}, {"valor": 14, "palabra": "nosotros-venceremos"}, {"valor": 14, "palabra": "general-división"}, {"valor": 14, "palabra": "trabajo-equipo"}, {"valor": 14, "palabra": "instituto-municipal"}, {"valor": 13, "palabra": "gobernador-primitivo"}, {"valor": 13, "palabra": "maduro-primitivo"}, {"valor": 13, "palabra": "armada-nacional"}, {"valor": 13, "palabra": "nacional-bolivariana"}, {"valor": 13, "palabra": "histórica-batalla"}, {"valor": 12, "palabra": "maduro-gobernador"}, {"valor": 12, "palabra": "equipo-triunfo"}, {"valor": 12, "palabra": "triunfo-seguro"}, {"valor": 11, "palabra": "dominio-español"}, {"valor": 11, "palabra": "historia-venezuela"}, {"valor": 11, "palabra": "ejército-libertador"}, {"valor": 11, "palabra": "terraza-triada"}, {"valor": 10, "palabra": "próceres-patria"}, {"valor": 10, "palabra": "importantes-historia"}], "VEN - CORINA MACHADO - IG": [{"valor": 37, "palabra": "corina-machado"}, {"valor": 34, "palabra": "edmundo-gonzález"}, {"valor": 23, "palabra": "edmundo-presidente"}, {"valor": 14, "palabra": "gonzález-urrutia"}, {"valor": 10, "palabra": "presidente-venezuela"}, {"valor": 9, "palabra": "libertad-venezuela"}, {"valor": 8, "palabra": "venezuela-venezolanos"}, {"valor": 8, "palabra": "corina-edmundo"}, {"valor": 7, "palabra": "dientes-edmundo"}, {"valor": 7, "palabra": "batalla-carabobo"}, {"valor": 7, "palabra": "estado-cojedes"}, {"valor": 7, "palabra": "venezuela-libertad"}, {"valor": 7, "palabra": "libertad-libertad"}, {"valor": 6, "palabra": "candidato-edmundo"}, {"valor": 6, "palabra": "venezuela-corina"}, {"valor": 6, "palabra": "machado-edmundo"}, {"valor": 6, "palabra": "llevando-mensaje"}, {"valor": 6, "palabra": "venezuela-venezuela"}, {"valor": 5, "palabra": "estados-unidos"}, {"valor": 5, "palabra": "matrimonio-igualitario"}, {"valor": 5, "palabra": "comando-campaña"}, {"valor": 5, "palabra": "hombres-mujeres"}, {"valor": 5, "palabra": "edmundo-corina"}, {"valor": 5, "palabra": "venezuela-edmundo"}, {"valor": 4, "palabra": "bendiga-siempre"}, {"valor": 4, "palabra": "corina-mérida"}, {"valor": 4, "palabra": "democracia-libertad"}, {"valor": 4, "palabra": "gracias-equipo"}, {"valor": 4, "palabra": "veremos-crecer"}, {"valor": 4, "palabra": "crecer-padres"}], "VEN - EDMUNDO GONZALEZ URRUTIA - ING": [{"valor": 24, "palabra": "gonzález-urrutia"}, {"valor": 21, "palabra": "edmundo-gonzález"}, {"valor": 6, "palabra": "corina-machado"}, {"valor": 6, "palabra": "presidente-edmundo"}, {"valor": 5, "palabra": "próximo-presidente"}, {"valor": 5, "palabra": "zulianos-edmundo"}, {"valor": 5, "palabra": "edmundo-presidente"}, {"valor": 4, "palabra": "tarjeta-unidad"}, {"valor": 3, "palabra": "compromiso-venezuela"}, {"valor": 3, "palabra": "llevando-mensaje"}, {"valor": 3, "palabra": "elecciones-presidenciales"}, {"valor": 3, "palabra": "venezuela-soberana"}, {"valor": 3, "palabra": "edmundo-corina"}, {"valor": 3, "palabra": "batalla-carabobo"}, {"valor": 3, "palabra": "futuro-presidente"}, {"valor": 2, "palabra": "candidato-edmundo"}, {"valor": 2, "palabra": "ejercer-derecho"}, {"valor": 2, "palabra": "soberana-confío"}, {"valor": 2, "palabra": "edmundo-venezuela"}, {"valor": 2, "palabra": "dibujo-edmundo"}, {"valor": 2, "palabra": "gracias-edmundo"}, {"valor": 2, "palabra": "contacto-directo"}, {"valor": 2, "palabra": "unidad-manito"}, {"valor": 2, "palabra": "trabajo-equipo"}, {"valor": 2, "palabra": "compromiso-mollejuo"}, {"valor": 2, "palabra": "eduardo-labrador"}, {"valor": 2, "palabra": "labrador-coordinador"}, {"valor": 2, "palabra": "francisco-enseñar"}, {"valor": 2, "palabra": "nicolás-maduro"}, {"valor": 2, "palabra": "votantes-registrados"}], "VEN - Nicolás Maduro - IG": [{"valor": 3, "palabra": "nicolás-maduro"}, {"valor": 3, "palabra": "cristóbal-mendoza"}, {"valor": 2, "palabra": "leales-siempre"}, {"valor": 2, "palabra": "siempre-traidores"}, {"valor": 2, "palabra": "victoria-siempre"}, {"valor": 2, "palabra": "cristobal-mendoza"}, {"valor": 2, "palabra": "estamos-contigo"}, {"valor": 2, "palabra": "excelente-presidente"}, {"valor": 2, "palabra": "venezolanos-estamos"}, {"valor": 2, "palabra": "presidente-maduro"}, {"valor": 2, "palabra": "maduro-presidente"}, {"valor": 2, "palabra": "pueblo-venezolano"}, {"valor": 2, "palabra": "nosotros-venceremos"}, {"valor": 2, "palabra": "venceremos-patria"}, {"valor": 2, "palabra": "presidente-pueblo"}, {"valor": 1, "palabra": "patria-brujos"}, {"valor": 1, "palabra": "brujos-presidente"}, {"valor": 1, "palabra": "presidente-comprando"}, {"valor": 1, "palabra": "comprando-jajajaja"}, {"valor": 1, "palabra": "jajajaja-creyendo"}, {"valor": 1, "palabra": "creyendo-vuelan"}, {"valor": 1, "palabra": "vuelan-jajajajaba"}, {"valor": 1, "palabra": "jajajajaba-andante"}, {"valor": 1, "palabra": "andante-presidiario"}, {"valor": 1, "palabra": "presidiario-estado"}, {"valor": 1, "palabra": "estado-monagas"}, {"valor": 1, "palabra": "monagas-municipio"}, {"valor": 1, "palabra": "municipio-caripe"}, {"valor": 1, "palabra": "caripe-decimos"}, {"valor": 1, "palabra": "decimos-leales"}], "VEN - CORINA YORIS - IG": [{"valor": 1, "palabra": "gracias-estimada"}, {"valor": 1, "palabra": "estimada-corina"}, {"valor": 1, "palabra": "corina-valioso"}, {"valor": 1, "palabra": "valioso-aporte"}, {"valor": 1, "palabra": "aporte-olvidaremos"}, {"valor": 1, "palabra": "olvidaremos-compromiso"}, {"valor": 1, "palabra": "compromiso-estarás"}, {"valor": 1, "palabra": "estarás-libros"}, {"valor": 1, "palabra": "libros-venezuela"}, {"valor": 1, "palabra": "venezuela-admiro"}, {"valor": 1, "palabra": "admiro-espero"}, {"valor": 1, "palabra": "espero-conocerte"}, {"valor": 1, "palabra": "conocerte-pronto"}]}, "2024-06-25-2024-06-25": {"VEN - Figuras opositoras - IG": [{"valor": 15, "palabra": "edmundo-gonzález"}, {"valor": 12, "palabra": "edmundo-presidente"}, {"valor": 9, "palabra": "gonzález-urrutia"}, {"valor": 4, "palabra": "corina-machado"}, {"valor": 4, "palabra": "guaido-inabilitada"}, {"valor": 3, "palabra": "urrutia-presidente"}, {"valor": 3, "palabra": "presidente-venezuela"}, {"valor": 3, "palabra": "seremos-libres"}, {"valor": 3, "palabra": "venezuela-edmundo"}, {"valor": 3, "palabra": "próximo-presidente"}, {"valor": 3, "palabra": "tengan-presente"}, {"valor": 3, "palabra": "presente-nombres"}, {"valor": 3, "palabra": "puente-angostura"}, {"valor": 3, "palabra": "candidato-unitario"}, {"valor": 3, "palabra": "unitario-edmundo"}, {"valor": 3, "palabra": "seguimos-adelante"}, {"valor": 3, "palabra": "nuestras-populares"}, {"valor": 3, "palabra": "simulacro-simulacro"}, {"valor": 3, "palabra": "gracias-sabotaje"}, {"valor": 3, "palabra": "sabotaje-bloqueo"}, {"valor": 3, "palabra": "bloqueo-guaido"}, {"valor": 3, "palabra": "excelente-trabajo"}, {"valor": 2, "palabra": "fuerza-armada"}, {"valor": 2, "palabra": "edmundo-maduro"}, {"valor": 2, "palabra": "pueblo-vencido"}, {"valor": 2, "palabra": "haciendo-campaña"}, {"valor": 2, "palabra": "gonzález-corina"}, {"valor": 2, "palabra": "fuerzas-armadas"}, {"valor": 2, "palabra": "quieren-cambio"}, {"valor": 2, "palabra": "siente-edmundo"}], "VEN - Medios afines - IG": [{"valor": 17, "palabra": "nicolás-maduro"}, {"valor": 12, "palabra": "presidente-república"}, {"valor": 12, "palabra": "bolivariana-venezuela"}, {"valor": 11, "palabra": "república-bolivariana"}, {"valor": 10, "palabra": "venezuela-nicolás"}, {"valor": 10, "palabra": "julian-assange"}, {"valor": 9, "palabra": "edmundo-gonzález"}, {"valor": 8, "palabra": "visita-puesto"}, {"valor": 7, "palabra": "fuerza-armada"}, {"valor": 6, "palabra": "armada-nacional"}, {"valor": 5, "palabra": "excelente-noticia"}, {"valor": 5, "palabra": "elecciones-presidenciales"}, {"valor": 4, "palabra": "edmundo-presidente"}, {"valor": 4, "palabra": "corina-machado"}, {"valor": 4, "palabra": "estados-unidos"}, {"valor": 4, "palabra": "comando-campaña"}, {"valor": 4, "palabra": "candidato-presidencial"}, {"valor": 4, "palabra": "presidenciales-próximo"}, {"valor": 4, "palabra": "canonización-gregorio"}, {"valor": 4, "palabra": "presidente-nicolás"}, {"valor": 3, "palabra": "transmisión-programa"}, {"valor": 3, "palabra": "sistema-eléctrico"}, {"valor": 3, "palabra": "assange-ejemplo"}, {"valor": 3, "palabra": "centro-votación"}, {"valor": 3, "palabra": "estado-falcón"}, {"valor": 3, "palabra": "sanciones-contra"}, {"valor": 3, "palabra": "contra-venezuela"}, {"valor": 3, "palabra": "pueblo-municipio"}, {"valor": 3, "palabra": "estado-guaira"}, {"valor": 3, "palabra": "gonzález-urrutia"}], "VEN - Medios adversos - IG": [{"valor": 26, "palabra": "estados-unidos"}, {"valor": 26, "palabra": "artículo-completo"}, {"valor": 25, "palabra": "gregorio-hernández"}, {"valor": 24, "palabra": "elecciones-presidenciales"}, {"valor": 20, "palabra": "edmundo-presidente"}, {"valor": 19, "palabra": "nicolás-maduro"}, {"valor": 18, "palabra": "edmundo-gonzález"}, {"valor": 15, "palabra": "también-puedes"}, {"valor": 14, "palabra": "conoce-también"}, {"valor": 14, "palabra": "corina-machado"}, {"valor": 14, "palabra": "fuerza-armada"}, {"valor": 14, "palabra": "proceso-electoral"}, {"valor": 13, "palabra": "armada-nacional"}, {"valor": 13, "palabra": "canonización-gregorio"}, {"valor": 11, "palabra": "naciones-unidas"}, {"valor": 11, "palabra": "expertos-electorales"}, {"valor": 10, "palabra": "julian-assange"}, {"valor": 9, "palabra": "gonzález-urrutia"}, {"valor": 9, "palabra": "fuerzas-armadas"}, {"valor": 9, "palabra": "secretario-general"}, {"valor": 9, "palabra": "consejo-nacional"}, {"valor": 9, "palabra": "canonizar-médico"}, {"valor": 8, "palabra": "privados-libertad"}, {"valor": 8, "palabra": "maduro-aseguró"}, {"valor": 8, "palabra": "nacional-electoral"}, {"valor": 8, "palabra": "periodista-rodríguez"}, {"valor": 8, "palabra": "sistema-eléctrico"}, {"valor": 8, "palabra": "médico-pobres"}, {"valor": 7, "palabra": "gonzález-presidente"}, {"valor": 7, "palabra": "millones-dólares"}], "VEN - Figuras afines - IG": [{"valor": 85, "palabra": "nicolás-maduro"}, {"valor": 55, "palabra": "presidente-nicolás"}, {"valor": 50, "palabra": "terraza-triada"}, {"valor": 45, "palabra": "primitivo-cedeño"}, {"valor": 30, "palabra": "triada-araure"}, {"valor": 23, "palabra": "gobernador-primitivo"}, {"valor": 17, "palabra": "edmundo-presidente"}, {"valor": 17, "palabra": "terrazas-tríada"}, {"valor": 17, "palabra": "tríada-araure"}, {"valor": 16, "palabra": "nosotros-venceremos"}, {"valor": 16, "palabra": "héctor-rodríguez"}, {"valor": 16, "palabra": "terraza-tríada"}, {"valor": 15, "palabra": "victoria-siempre"}, {"valor": 15, "palabra": "ejército-bolivariano"}, {"valor": 14, "palabra": "batalla-carabobo"}, {"valor": 14, "palabra": "pueblo-venezolano"}, {"valor": 14, "palabra": "estado-portuguesa"}, {"valor": 11, "palabra": "maduro-primitivo"}, {"valor": 11, "palabra": "venezuela-siempre"}, {"valor": 11, "palabra": "coordinador-nacional"}, {"valor": 11, "palabra": "maduro-terraza"}, {"valor": 10, "palabra": "siempre-traidores"}, {"valor": 10, "palabra": "gobierno-bolivariano"}, {"valor": 9, "palabra": "victoria-presidente"}, {"valor": 9, "palabra": "diosdado-cabello"}, {"valor": 9, "palabra": "seguridad-ciudadana"}, {"valor": 9, "palabra": "clínica-popular"}, {"valor": 9, "palabra": "maduro-gobernador"}, {"valor": 9, "palabra": "entrega-insumos"}, {"valor": 9, "palabra": "insumos-médicos"}], "VEN - CORINA MACHADO - IG": [{"valor": 32, "palabra": "corina-machado"}, {"valor": 30, "palabra": "edmundo-presidente"}, {"valor": 27, "palabra": "edmundo-gonzález"}, {"valor": 16, "palabra": "aleluya-aleluya"}, {"valor": 13, "palabra": "pueblo-quiere"}, {"valor": 12, "palabra": "presidente-venezuela"}, {"valor": 10, "palabra": "venezuela-edmundo"}, {"valor": 10, "palabra": "gonzález-urrutia"}, {"valor": 10, "palabra": "presidente-edmundo"}, {"valor": 9, "palabra": "jajajaja-jajajaja"}, {"valor": 8, "palabra": "corina-edmundo"}, {"valor": 8, "palabra": "dientes-edmundo"}, {"valor": 8, "palabra": "venezuela-libertad"}, {"valor": 8, "palabra": "estado-mérida"}, {"valor": 8, "palabra": "mérida-venezuela"}, {"valor": 7, "palabra": "bendiga-proteja"}, {"valor": 7, "palabra": "pueblo-venezolano"}, {"valor": 7, "palabra": "venezuela-venezuela"}, {"valor": 6, "palabra": "edmundo-corina"}, {"valor": 6, "palabra": "venezuela-corazón"}, {"valor": 6, "palabra": "caravana-libertad"}, {"valor": 6, "palabra": "comando-jóvenes"}, {"valor": 6, "palabra": "libertad-libertad"}, {"valor": 5, "palabra": "bendiga-siempre"}, {"valor": 5, "palabra": "gracias-venezuela"}, {"valor": 5, "palabra": "bendiciones-venezuela"}, {"valor": 5, "palabra": "próximo-presidente"}, {"valor": 5, "palabra": "nicolás-maduro"}, {"valor": 5, "palabra": "ciudad-mérida"}, {"valor": 5, "palabra": "gracias-gracias"}], "VEN - EDMUNDO GONZALEZ URRUTIA - ING": [{"valor": 61, "palabra": "pueblo-quiere"}, {"valor": 11, "palabra": "nicolás-maduro"}, {"valor": 10, "palabra": "chavista-pueblo"}, {"valor": 7, "palabra": "edmundo-gonzález"}, {"valor": 5, "palabra": "candidata-partido"}, {"valor": 5, "palabra": "partido-político"}, {"valor": 5, "palabra": "político-oposición"}, {"valor": 5, "palabra": "oposición-pueblo"}, {"valor": 5, "palabra": "pueblo-corrupción"}, {"valor": 5, "palabra": "corrupción-chavista"}, {"valor": 5, "palabra": "quiere-gasolina"}, {"valor": 5, "palabra": "gasolina-pueblo"}, {"valor": 5, "palabra": "quiere-apagones"}, {"valor": 5, "palabra": "apagones-pueblo"}, {"valor": 5, "palabra": "quiere-delincuencia"}, {"valor": 5, "palabra": "delincuencia-pueblo"}, {"valor": 5, "palabra": "quiere-corrupción"}, {"valor": 5, "palabra": "corrupción-pueblo"}, {"valor": 5, "palabra": "quiere-pueblo"}, {"valor": 5, "palabra": "quiere-corpoelec"}, {"valor": 5, "palabra": "corpoelec-hidrológicas"}, {"valor": 5, "palabra": "hidrológicas-movistar"}, {"valor": 5, "palabra": "movistar-digitel"}, {"valor": 5, "palabra": "digitel-movilnet"}, {"valor": 5, "palabra": "movilnet-pueblo"}, {"valor": 5, "palabra": "quiere-matraqueo"}, {"valor": 5, "palabra": "matraqueo-alcabalas"}, {"valor": 5, "palabra": "alcabalas-pueblo"}, {"valor": 5, "palabra": "quiere-precios"}, {"valor": 5, "palabra": "precios-alcaldías"}], "VEN - Nicolás Maduro - IG": [{"valor": 3, "palabra": "fuerza-armada"}, {"valor": 3, "palabra": "nicolas-maduro"}, {"valor": 2, "palabra": "venceremos-venceremos"}, {"valor": 2, "palabra": "snacks-falsos"}, {"valor": 2, "palabra": "nosotros-venceremos"}, {"valor": 2, "palabra": "siendo-nicolas"}, {"valor": 2, "palabra": "maduro-venceremos"}, {"valor": 2, "palabra": "presidente-nicolás"}, {"valor": 2, "palabra": "alejandro-maduro"}, {"valor": 2, "palabra": "saludos-cordiales"}, {"valor": 2, "palabra": "queremos-queremos"}, {"valor": 1, "palabra": "edmundo-presidente"}, {"valor": 1, "palabra": "presidente-acabaron"}, {"valor": 1, "palabra": "acabaron-milicia"}, {"valor": 1, "palabra": "milicia-actitud"}, {"valor": 1, "palabra": "actitud-triste"}, {"valor": 1, "palabra": "triste-decadente"}, {"valor": 1, "palabra": "decadente-ministro"}, {"valor": 1, "palabra": "ministro-fuerza"}, {"valor": 1, "palabra": "armada-pagarás"}, {"valor": 1, "palabra": "pagarás-permitido"}, {"valor": 1, "palabra": "permitido-faltaran"}, {"valor": 1, "palabra": "faltaran-haddan"}, {"valor": 1, "palabra": "haddan-volveran"}, {"valor": 1, "palabra": "volveran-maduro"}, {"valor": 1, "palabra": "maduro-maldito"}, {"valor": 1, "palabra": "maldito-poquito"}, {"valor": 1, "palabra": "poquito-exelente"}, {"valor": 1, "palabra": "exelente-titere"}, {"valor": 1, "palabra": "titere-maduro"}], "VEN - CORINA YORIS - IG": [{"valor": 1, "palabra": "buenos-buenos"}, {"valor": 1, "palabra": "buenos-juntos"}, {"valor": 1, "palabra": "juntos-amarillas"}, {"valor": 1, "palabra": "amarillas-hermoso"}, {"valor": 1, "palabra": "hermoso-gracias"}, {"valor": 1, "palabra": "gracias-compartir"}, {"valor": 1, "palabra": "compartir-ramodios"}, {"valor": 1, "palabra": "ramodios-disfrutes"}, {"valor": 1, "palabra": "disfrutes-fuerza"}, {"valor": 1, "palabra": "fuerza-nosotros"}, {"valor": 1, "palabra": "nosotros-hermoso"}, {"valor": 1, "palabra": "hermoso-arreglo"}, {"valor": 1, "palabra": "arreglo-disfrutes"}]}}